DBAppParser/DbAppParser.py
DBAppParser/__init__.py
bdrc_DBAppParser-1.0.4.dist-info/METADATA
bdrc_DBAppParser-1.0.4.dist-info/WHEEL
bdrc_DBAppParser-1.0.4.dist-info/top_level.txt
bdrc_DBAppParser-1.0.4.dist-info/RECORD
