Metadata-Version: 2.1
Name: bdrc-DBAppParser
Version: 1.0.4
Summary: # BDRC DbApp ParserCommon arg parsing libraries for bdrc-utils
Home-page: UNKNOWN
Author: jimk
Author-email: jimk@tbrc.org
License: MIT
Platform: UNKNOWN
Classifier: Programming Language :: Python :: 3
Classifier: License :: OSI Approved :: MIT License
Classifier: Operating System :: MacOS :: MacOS X
Classifier: Operating System :: OS Independent
Classifier: Development Status :: 5 - Production/Stable
Requires-Python: >=3.7
